<window id="123">
	<defaultcontrol always="true">5</defaultcontrol>
	<allowoverlay>yes</allowoverlay>

	<controls>
		
		<control type="label">
			<include>DialogID</include>
			<label>VideoOSDSettings.xml</label>
		</control>
				
		<control type="image">
			<posx>0</posx>
			<posy>0</posy>
			<width>fullscreenWidth</width>
			<height>fullscreenHeight</height>
			<aspectratio>stretch</aspectratio>
			<texture>colors/black.png</texture>
			<colordiffuse>ddFFFFFF</colordiffuse>
			<include>fadeInOut</include>	
		</control>
		
		<control type="group">
			
			<!--animations-->
			<include>modalDialogInOut</include>       
		
			<control type="group">
				<posx>col-7-begin</posx>
				<posy>row-3-begin</posy>

				<control type="label" id="2">
					<posx>0</posx>
					<posy>0</posy>
					<width>12-col-gutter</width>
					<font>pageTitle</font>
					<textcolor>white</textcolor>
				</control>
				
				<!--horizontal rule-->
				<control type="image">
					<posx>0</posx>
					<posy>1-row</posy>
					<width>12-col</width>
					<height>3</height>
					<texture>colors/white.png</texture>
					<colordiffuse>ffffffff</colordiffuse>
					<aspectratio>stretch</aspectratio>
				</control>
				
				<control type="grouplist" id="5">
					<description>Control Area</description>
					<posx>0</posx>
					<posy>2-row</posy>
					<width>12-col-gutter</width>
					<height>12-row</height>
					<orientation>vertical</orientation>
				</control>

				<control type="button" id="7">
					<description>Default Button</description>
					<align>left</align>
					<font>itemTitle</font>
					<textcolor>unselected</textcolor>
					<focusedcolor>white</focusedcolor>
				</control>

				<control type="radiobutton" id="8">
					<description>Default RadioButton</description>
					<align>left</align>
				</control>

				<control type="spincontrolex" id="9">
					<description>Default spincontrolex</description>
					<align>left</align>
					<reverse>yes</reverse>
				</control>

				<control type="sliderex" id="10">
					<description>Default Slider</description>
					<align>left</align>
				</control>
		
			</control>
		</control>

		<include>Debug_Grid</include>

	</controls>

</window>